sportslabkit/__init__.py
sportslabkit/calibration_model/__init__.py
sportslabkit/calibration_model/base.py
sportslabkit/calibration_model/dummy.py
sportslabkit/calibration_model/fld.py
sportslabkit/camera/__init__.py
sportslabkit/camera/calibrate.py
sportslabkit/camera/camera.py
sportslabkit/camera/videoreader.py
sportslabkit/checks.py
sportslabkit/cli.py
sportslabkit/constants.py
sportslabkit/dataframe/__init__.py
sportslabkit/dataframe/base.py
sportslabkit/dataframe/bboxdataframe.py
sportslabkit/dataframe/coordinatesdataframe.py
sportslabkit/dataframe/gpsdataframe.py
sportslabkit/datasets/G_20200220_1_0000_0030.csv
sportslabkit/datasets/__init__.py
sportslabkit/datasets/datasets/__init__.py
sportslabkit/datasets/datasets/trajectory_datamodule.py
sportslabkit/datasets/downloader.py
sportslabkit/detection_model/__init__.py
sportslabkit/detection_model/base.py
sportslabkit/detection_model/dummy.py
sportslabkit/detection_model/yolov8.py
sportslabkit/image_model/__init__.py
sportslabkit/image_model/base.py
sportslabkit/image_model/clip.py
sportslabkit/image_model/torchreid.py
sportslabkit/image_model/visualization.py
sportslabkit/io/__init__.py
sportslabkit/io/file.py
sportslabkit/logger.py
sportslabkit/matching/__init__.py
sportslabkit/matching/base.py
sportslabkit/matching/base_batch.py
sportslabkit/matching/motion_visual.py
sportslabkit/matching/simple.py
sportslabkit/metrics/__init__.py
sportslabkit/metrics/cost_matrix_metrics.py
sportslabkit/metrics/hota.py
sportslabkit/metrics/identity.py
sportslabkit/metrics/mota.py
sportslabkit/metrics/object_detection.py
sportslabkit/metrics/tracking_preprocess.py
sportslabkit/metrics/utils.py
sportslabkit/mot/__init__.py
sportslabkit/mot/base.py
sportslabkit/mot/bytetrack.py
sportslabkit/mot/callbacks.py
sportslabkit/mot/deepsort.py
sportslabkit/mot/sort.py
sportslabkit/mot/teamtrack.py
sportslabkit/motion_model/__init__.py
sportslabkit/motion_model/base.py
sportslabkit/motion_model/models/__init__.py
sportslabkit-0.3.1.dist-info/LICENSE
sportslabkit-0.3.1.dist-info/METADATA
sportslabkit-0.3.1.dist-info/WHEEL
sportslabkit-0.3.1.dist-info/RECORD
