Metadata-Version: 2.1
Name: sportslabkit
Version: 0.3.1
Summary: A Python package for sports analytics.
Home-page: https://github.com/AtomScott/SportsLabKit
License: GPL-3.0-or-later
Keywords: sports,analytics,data,science,machine,learning
Author: Atom Scott
Author-email: atom.james.scott@gmail.com
Requires-Python: >=3.10,<4.0
Classifier: Development Status :: 3 - Alpha
Classifier: Intended Audience :: Developers
Classifier: License :: OSI Approved :: GNU General Public License v3 or later (GPLv3+)
Classifier: Operating System :: OS Independent
Classifier: Programming Language :: Python :: 3
Classifier: Programming Language :: Python :: 3.10
Classifier: Programming Language :: Python :: 3.11
Requires-Dist: Cython
Requires-Dist: Pillow
Requires-Dist: black
Requires-Dist: docformatter (>=1.5.1,<2.0.0)
Requires-Dist: einops (>=0.6.0,<0.7.0)
Requires-Dist: ffmpeg-python (>=0.2.0,<0.3.0)
Requires-Dist: filterpy (>=1.4.5,<2.0.0)
Requires-Dist: fire (>=0.5.0,<0.6.0)
Requires-Dist: gdown (>=4.7.1,<5.0.0)
Requires-Dist: gitpython (>=3.1.30,<4.0.0)
Requires-Dist: ipython (>=8.5.0,<9.0.0)
Requires-Dist: jsonargparse[signatures] (==4.20.0)
Requires-Dist: kaggle (>=1.5.12,<2.0.0)
Requires-Dist: labelbox (>=3.35.0,<4.0.0)
Requires-Dist: loguru (>=0.6.0,<0.7.0)
Requires-Dist: mplsoccer (>=1.1.10,<2.0.0)
Requires-Dist: ndjson (>=0.3.1,<0.4.0)
Requires-Dist: networkx (>=3.1,<4.0)
Requires-Dist: numpy (>=1.22.4,<2.0.0)
Requires-Dist: omegaconf (>=2.2.2,<3.0.0)
Requires-Dist: opencv-contrib-python
Requires-Dist: optuna (>=3.1.1,<4.0.0)
Requires-Dist: pandas (>=1.4.2,<2.0.0)
Requires-Dist: protobuf (>=3.20.0,<4.0.0)
Requires-Dist: py-cpuinfo
Requires-Dist: python-dotenv (>=0.21.1,<0.22.0)
Requires-Dist: pytorch_lightning
Requires-Dist: rich (>=12.5.1,<13.0.0)
Requires-Dist: scikit-learn (>=1.2.1,<2.0.0)
Requires-Dist: scikit-video (>=1.1.11,<2.0.0)
Requires-Dist: scipy (>=1.8.1,<2.0.0)
Requires-Dist: seedir
Requires-Dist: six
Requires-Dist: tensorboard (>=2.11.2,<3.0.0)
Requires-Dist: torch
Requires-Dist: torchvision
Requires-Dist: types-python-dateutil (>=2.8.17,<3.0.0)
Requires-Dist: ultralytics
Requires-Dist: vidgear[core] (==0.3.0)
Requires-Dist: yacs
Project-URL: Documentation, https://sportslabkit.readthedocs.io/en/latest/
Project-URL: Repository, https://github.com/AtomScott/SportsLabKit
